kizamu_manga-1.0.1.dist-info/licenses/LICENSE
kizamumanga/__init__.py
kizamumanga/config.toml
kizamumanga/main.py
kizamumanga/engine/__init__.py
kizamumanga/engine/config.py
kizamumanga/engine/downloader.py
kizamumanga/engine/image_converter.py
kizamumanga/engine/paths.py
kizamumanga/engine/runner.py
kizamumanga/handlers/__init__.py
kizamumanga/handlers/args_handler.py
kizamumanga/scraping/__init__.py
kizamumanga/scraping/base.py
kizamumanga/scraping/inmanga.py
kizamumanga/scraping/interface.py
kizamumanga/scraping/leermangaesp.py
kizamumanga/scraping/weeb_central.py
kizamumanga/utils/__init__.py
kizamumanga/utils/ascii.py
kizamumanga/utils/general_tools.py
kizamumanga/utils/loading_spinner.py
kizamumanga/utils/logger.py
kizamu_manga-1.0.1.dist-info/METADATA
kizamu_manga-1.0.1.dist-info/WHEEL
kizamu_manga-1.0.1.dist-info/entry_points.txt
kizamu_manga-1.0.1.dist-info/top_level.txt
kizamu_manga-1.0.1.dist-info/RECORD
