Metadata-Version: 2.4
Name: kizamu-manga
Version: 1.0.1
Summary: CLI to search and download manga chapters -> exported to CBZ.
Author-email: Cocera Cia <coceraciamiguel@gmail.com>
License: MIT License
Project-URL: Homepage, https://github.com/CoceraCia/KizamuManga
Project-URL: Repository, https://github.com/CoceraCia/KizamuManga
Keywords: manga,scraping,downloader,playwright,cbz,cli,comic,asynchronous
Classifier: Programming Language :: Python :: 3
Classifier: Programming Language :: Python :: 3.9
Classifier: Programming Language :: Python :: 3.10
Classifier: Programming Language :: Python :: 3.11
Classifier: License :: OSI Approved :: MIT License
Classifier: Operating System :: OS Independent
Classifier: Topic :: Internet :: WWW/HTTP
Classifier: Topic :: Multimedia :: Graphics
Requires-Python: >=3.9
License-File: LICENSE
Requires-Dist: aiohttp>=3.12.14
Requires-Dist: beautifulsoup4>=4.13.4
Requires-Dist: playwright>=1.54.0
Requires-Dist: rich>=14.1.0
Requires-Dist: tenacity>=9.1.2
Requires-Dist: tomlkit>=0.13.3
Requires-Dist: pillow>=11.3.0
Requires-Dist: opencv-python>=4.12.0.88
Requires-Dist: numpy>=2.2.6
Dynamic: license-file
